main.py
memos.py
memos_mcp_server-0.1.0.dist-info/METADATA
memos_mcp_server-0.1.0.dist-info/WHEEL
memos_mcp_server-0.1.0.dist-info/entry_points.txt
memos_mcp_server-0.1.0.dist-info/top_level.txt
memos_mcp_server-0.1.0.dist-info/RECORD
